robocrys/__init__.py
robocrys/_version.py
robocrys/adapter.py
robocrys/cli.py
robocrys/condense/__init__.py
robocrys/condense/component.py
robocrys/condense/condenser.py
robocrys/condense/fingerprint.py
robocrys/condense/formula_db.json.gz
robocrys/condense/mineral.py
robocrys/condense/mineral_db.json.gz
robocrys/condense/molecule.py
robocrys/condense/molecule_db.json.gz
robocrys/condense/site.py
robocrys/describe/__init__.py
robocrys/describe/adapter.py
robocrys/describe/describer.py
robocrys/featurize/__init__.py
robocrys/featurize/adapter.py
robocrys/featurize/featurizer.py
robocrys/util/__init__.py
robocrys/util/tests.py
robocrys/util/util.py
robocrys-0.2.11.data/data/CONTRIBUTING.rst
robocrys-0.2.11.data/data/LICENSE
robocrys-0.2.11.dist-info/LICENSE
robocrys-0.2.11.dist-info/METADATA
robocrys-0.2.11.dist-info/WHEEL
robocrys-0.2.11.dist-info/entry_points.txt
robocrys-0.2.11.dist-info/top_level.txt
robocrys-0.2.11.dist-info/RECORD
