Metadata-Version: 2.1
Name: robocrys
Version: 0.2.11
Summary: Automatic generation of crystal structure descriptions
Home-page: https://github.com/hackingmaterials/robocrystallographer
Author: Alex Ganose
Author-email: aganose@lbl.gov
License: modified BSD
Keywords: crystal-structure crystallography materials-science
Classifier: Development Status :: 3 - Alpha
Classifier: Intended Audience :: Science/Research
Classifier: Intended Audience :: Information Technology
Classifier: License :: OSI Approved :: MIT License
Classifier: Natural Language :: English
Classifier: Programming Language :: Python :: 3 :: Only
Classifier: Programming Language :: Python :: 3.7
Classifier: Programming Language :: Python :: 3.8
Classifier: Programming Language :: Python :: 3.9
Classifier: Topic :: Scientific/Engineering :: Chemistry
Classifier: Topic :: Scientific/Engineering :: Physics
Classifier: Topic :: Scientific/Engineering
Classifier: Topic :: Other/Nonlisted Topic
Classifier: Operating System :: OS Independent
Requires-Python: >=3.8
License-File: LICENSE
Requires-Dist: inflect
Requires-Dist: matminer >=0.9.2
Requires-Dist: monty
Requires-Dist: networkx
Requires-Dist: numpy
Requires-Dist: pubchempy
Requires-Dist: pybtex
Requires-Dist: pymatgen >=2024.1.26
Requires-Dist: ruamel.yaml
Requires-Dist: scipy
Requires-Dist: spglib >=2.5.0
Provides-Extra: cli
Requires-Dist: mp-api ; extra == 'cli'
Provides-Extra: dev
Requires-Dist: maggma ; extra == 'dev'
Requires-Dist: pebble ; extra == 'dev'
Requires-Dist: pybel ; extra == 'dev'
Requires-Dist: tqdm ; extra == 'dev'
Provides-Extra: docs
Requires-Dist: m2r2 ==0.3.2 ; extra == 'docs'
Requires-Dist: sphinx-argparse ==0.4.0 ; extra == 'docs'
Requires-Dist: sphinx-autodoc-typehints ==1.23.0 ; extra == 'docs'
Requires-Dist: sphinx ==5.3.0 ; extra == 'docs'
Requires-Dist: sphinx-rtd-theme ==1.2.0 ; extra == 'docs'
Provides-Extra: lint
Requires-Dist: black ==24.8.0 ; extra == 'lint'
Requires-Dist: codacy-coverage ==1.3.11 ; extra == 'lint'
Requires-Dist: coverage ==7.6.1 ; extra == 'lint'
Requires-Dist: flake8 ==7.1.1 ; extra == 'lint'
Requires-Dist: mypy ==1.11.2 ; extra == 'lint'
Requires-Dist: pycodestyle ==2.11.1 ; extra == 'lint'
Requires-Dist: pydocstyle ==6.1.1 ; extra == 'lint'
Requires-Dist: pylint ==3.3.1 ; extra == 'lint'
Provides-Extra: tests
Requires-Dist: pytest-cov ==5.0.0 ; extra == 'tests'
Requires-Dist: pytest ==8.3.3 ; extra == 'tests'
